{
  "version": "1.1.0",
  "release_date": "2025-10-09",
  "download_url": "https://github.com/jlaiii/RUST-BM-AFK/releases/latest",
  "github_url": "https://github.com/jlaiii/RUST-BM-AFK",
  "changelog": [
    "Added automatic self-update system",
    "Update notifications with changelog preview",
    "One-click updates with progress tracking",
    "Automatic backup creation during updates",
    "Enhanced version management",
    "Improved error handling for updates"
  ],
  "version_history": [
    {
      "version": "1.1.0",
      "release_date": "2025-10-09",
      "changelog": [
        "Added automatic self-update system",
        "Update notifications with changelog preview",
        "One-click updates with progress tracking",
        "Automatic backup creation during updates",
        "Enhanced version management",
        "Improved error handling for updates"
      ]
    },
    {
      "version": "1.0.0",
      "release_date": "2025-10-09",
      "changelog": [
        "First public release"
      ]
    }
  ]
}